{
  "parent": "minecraft:recipes/root",
  "criteria": {
    "has_stem": {
      "conditions": {
        "items": [
          {
            "tag": "wilderwild:hollowed_crimson_stems"
          }
        ]
      },
      "trigger": "minecraft:inventory_changed"
    },
    "has_the_recipe": {
      "conditions": {
        "recipe": "wilderwild:crimson_planks_from_hollowed"
      },
      "trigger": "minecraft:recipe_unlocked"
    }
  },
  "requirements": [
    [
      "has_stem",
      "has_the_recipe"
    ]
  ],
  "rewards": {
    "recipes": [
      "wilderwild:crimson_planks_from_hollowed"
    ]
  },
  "sends_telemetry_event": false
}