{
  "type": "minecraft:simple_block",
  "config": {
    "to_place": {
      "type": "minecraft:noise_provider",
      "noise": {
        "amplitudes": [
          1.0
        ],
        "firstOctave": 0
      },
      "scale": 0.048833333,
      "seed": 5050,
      "states": [
        {
          "Name": "minecraft:azure_bluet"
        },
        {
          "Name": "minecraft:lily_of_the_valley"
        },
        {
          "Name": "minecraft:dandelion"
        },
        {
          "Name": "minecraft:poppy"
        },
        {
          "Name": "wilderwild:carnation"
        },
        {
          "Name": "minecraft:allium"
        },
        {
          "Name": "minecraft:oxeye_daisy"
        }
      ]
    }
  }
}